graphix/__init__.py
graphix/_db.py
graphix/_version.py
graphix/branch_selector.py
graphix/channels.py
graphix/clifford.py
graphix/command.py
graphix/extraction.py
graphix/fundamentals.py
graphix/generator.py
graphix/gflow.py
graphix/graphsim.py
graphix/instruction.py
graphix/linalg.py
graphix/linalg_validations.py
graphix/measurements.py
graphix/opengraph.py
graphix/ops.py
graphix/optimization.py
graphix/parameter.py
graphix/pattern.py
graphix/pauli.py
graphix/pretty_print.py
graphix/py.typed
graphix/pyzx.py
graphix/random_objects.py
graphix/repr_mixins.py
graphix/rng.py
graphix/simulator.py
graphix/states.py
graphix/transpiler.py
graphix/utils.py
graphix/visualization.py
graphix/noise_models/__init__.py
graphix/noise_models/noise_model.py
graphix/noise_models/noiseless_noise_model.py
graphix/sim/__init__.py
graphix/sim/base_backend.py
graphix/sim/data.py
graphix/sim/density_matrix.py
graphix/sim/statevec.py
graphix/sim/tensornet.py
graphix-0.3.2.dist-info/licenses/LICENSE
stubs/quimb/__init__.pyi
stubs/quimb/tensor/__init__.pyi
graphix-0.3.2.dist-info/METADATA
graphix-0.3.2.dist-info/WHEEL
graphix-0.3.2.dist-info/top_level.txt
graphix-0.3.2.dist-info/RECORD
