Metadata-Version: 2.4
Name: graphix
Version: 0.3.2
Summary: Optimize and simulate measurement-based quantum computation
Author-email: Shinichi Sunami <shinichi.sunami@gmail.com>
Maintainer-email: Shinichi Sunami <shinichi.sunami@gmail.com>
Project-URL: Documentation, https://graphix.readthedocs.io
Project-URL: Bug Tracker, https://github.com/TeamGraphix/graphix/issues
Classifier: Development Status :: 4 - Beta
Classifier: Environment :: Console
Classifier: Intended Audience :: Science/Research
Classifier: Programming Language :: Python :: 3.9
Classifier: Programming Language :: Python :: 3.10
Classifier: Programming Language :: Python :: 3.11
Classifier: Programming Language :: Python :: 3.12
Classifier: Programming Language :: Python :: 3.13
Classifier: Operating System :: OS Independent
Classifier: Topic :: Scientific/Engineering :: Physics
Requires-Python: <3.14,>=3.9
License-File: LICENSE
Requires-Dist: galois
Requires-Dist: matplotlib
Requires-Dist: networkx
Requires-Dist: numpy<3,>=2
Requires-Dist: opt_einsum
Requires-Dist: quimb
Requires-Dist: scipy
Requires-Dist: sympy
Requires-Dist: typing_extensions
Provides-Extra: dev
Requires-Dist: mypy==1.17.1; extra == "dev"
Requires-Dist: pre-commit; extra == "dev"
Requires-Dist: pyright; extra == "dev"
Requires-Dist: ruff==0.12.9; extra == "dev"
Requires-Dist: types-networkx==3.5.0.20250712; extra == "dev"
Requires-Dist: types-psutil; extra == "dev"
Requires-Dist: types-setuptools; extra == "dev"
Requires-Dist: nox==2025.5.1; extra == "dev"
Requires-Dist: psutil; extra == "dev"
Requires-Dist: pytest; extra == "dev"
Requires-Dist: pytest-cov; extra == "dev"
Requires-Dist: pytest-mock; extra == "dev"
Requires-Dist: qiskit>=1.0; extra == "dev"
Requires-Dist: qiskit-aer; extra == "dev"
Provides-Extra: extra
Requires-Dist: pyzx==0.9.0; extra == "extra"
Provides-Extra: doc
Requires-Dist: furo; extra == "doc"
Requires-Dist: joblib; extra == "doc"
Requires-Dist: matplotlib; extra == "doc"
Requires-Dist: sphinx; extra == "doc"
Requires-Dist: sphinx-gallery; extra == "doc"
Dynamic: license-file
